wolfcrypt/random.py
wolfcrypt/_ffi.abi3.so
wolfcrypt/exceptions.py
wolfcrypt/_build_ffi.py
wolfcrypt/utils.py
wolfcrypt/hashes.py
wolfcrypt/_build_wolfssl.py
wolfcrypt/__init__.py
wolfcrypt/ciphers.py
wolfcrypt-4.1.0.post0.dist-info/WHEEL
wolfcrypt-4.1.0.post0.dist-info/RECORD
wolfcrypt-4.1.0.post0.dist-info/top_level.txt
wolfcrypt-4.1.0.post0.dist-info/METADATA
