Metadata-Version: 2.1
Name: wolfcrypt
Version: 4.1.0.post0
Summary: Python module that encapsulates wolfSSL's crypto engine API.
Home-page: https://github.com/wolfssl/wolfcrypt-py
Author: wolfSSL Inc.
Author-email: info@wolfssl.com
License: GPLv2 or Commercial License
Keywords: wolfssl,wolfcrypt,security,cryptography
Platform: UNKNOWN
Classifier: License :: OSI Approved :: GNU General Public License v2 (GPLv2)
Classifier: License :: Other/Proprietary License
Classifier: Operating System :: OS Independent
Classifier: Programming Language :: Python :: 2.7
Classifier: Programming Language :: Python :: 3.4
Classifier: Programming Language :: Python :: 3.5
Classifier: Programming Language :: Python :: 3.6
Classifier: Topic :: Security
Classifier: Topic :: Security :: Cryptography
Classifier: Topic :: Software Development
Requires-Dist: cffi
